TemporalBackbone/__init__.py
TemporalBackbone-0.1.6.dist-info/LICENSE
TemporalBackbone-0.1.6.dist-info/METADATA
TemporalBackbone-0.1.6.dist-info/WHEEL
TemporalBackbone-0.1.6.dist-info/top_level.txt
TemporalBackbone-0.1.6.dist-info/RECORD
