Metadata-Version: 2.1
Name: TemporalBackbone
Version: 0.1.6
Summary: A tool to detect the backbone in temporal networks
Home-page: https://github.com/matnado/TemporalBackbone
Author: Matthieu Nadini
Author-email: matthieu.nadini@gmail.com
License: UNKNOWN
Platform: UNKNOWN
Classifier: Programming Language :: Python :: 3
Classifier: License :: OSI Approved :: GNU General Public License v3 (GPLv3)
Classifier: Operating System :: POSIX :: Linux
Requires-Python: >=3.6
